README.md
setup.cfg
setup.py
contextlib_ext/__init__.py
contextlib_ext.egg-info/PKG-INFO
contextlib_ext.egg-info/SOURCES.txt
contextlib_ext.egg-info/dependency_links.txt
contextlib_ext.egg-info/top_level.txt