Metadata-Version: 2.1
Name: contextlib-ext
Version: 0.0.0
Summary: Extensions for contextlib
Home-page: https://github.com/nikicat/contextlib-ext
Author: Nikolay Bryskin
Author-email: nbryskin@gmail.com
License: UNKNOWN
Project-URL: Bug Reports, https://github.com/nikicat/contextlib-ext/issues
Project-URL: Source, https://github.com/nikicat/contextlib-ext/
Keywords: contextlib async development
Platform: UNKNOWN
Classifier: Development Status :: 3 - Alpha
Classifier: Intended Audience :: Developers
Classifier: Topic :: Software Development :: Build Tools
Classifier: License :: OSI Approved :: MIT License
Classifier: Programming Language :: Python :: 3
Classifier: Programming Language :: Python :: 3.7
Classifier: Programming Language :: Python :: 3.8
Requires-Python: >=3.7, <4
